redshifting/__init__.py
redshifting/main.py
redshifting-1.3.dist-info/METADATA
redshifting-1.3.dist-info/WHEEL
redshifting-1.3.dist-info/top_level.txt
redshifting-1.3.dist-info/RECORD
