Metadata-Version: 2.1
Name: redshifting
Version: 1.3
Summary: Redshift a radio source to a higher redshift
Home-page: UNKNOWN
Author: Jurjen de Jong
Author-email: <jurjong@proton.me>
License: UNKNOWN
Keywords: python,redshifting,radio astronomy
Platform: UNKNOWN
Requires-Dist: astropy
Requires-Dist: reproject
Requires-Dist: matplotlib
Requires-Dist: numpy
